{
    "format_version": "1.20.80",
    "minecraft:recipe_shapeless": {
        "description": {
            "identifier": "utilitycraft:craft_diorite_bricks"
        },
        "tags": [
            "crafting_table"
        ],
        "ingredients": [
            {
                "item": "minecraft:polished_diorite",
                "count": 4
            }
        ],
        "result": {
            "item": "utilitycraft:diorite_bricks",
            "count": 4
        },
        "unlock": [
            {
                "item": "minecraft:polished_diorite"
            }
        ]
    }
}